MANIFEST.in
setup.py
docs/HISTORY.txt
src/dolmen/__init__.py
src/dolmen.widget.file.egg-info/PKG-INFO
src/dolmen.widget.file.egg-info/SOURCES.txt
src/dolmen.widget.file.egg-info/dependency_links.txt
src/dolmen.widget.file.egg-info/namespace_packages.txt
src/dolmen.widget.file.egg-info/not-zip-safe
src/dolmen.widget.file.egg-info/requires.txt
src/dolmen.widget.file.egg-info/top_level.txt
src/dolmen/widget/__init__.py
src/dolmen/widget/file/README.txt
src/dolmen/widget/file/__init__.py
src/dolmen/widget/file/configure.zcml
src/dolmen/widget/file/converter.py
src/dolmen/widget/file/ftesting.zcml
src/dolmen/widget/file/tests.py
src/dolmen/widget/file/widget.py
src/dolmen/widget/file/templates/display.pt
src/dolmen/widget/file/templates/input.pt